README.rst
setup.py
motif/__init__.py
motif/motif.py
motif.egg-info/PKG-INFO
motif.egg-info/SOURCES.txt
motif.egg-info/dependency_links.txt
motif.egg-info/top_level.txt