Metadata-Version: 1.0
Name: motif
Version: 0.0.10
Summary: motif - Python module written by Wu Fuheng
Home-page: http://www.quant365.com
Author: Wu Fuheng
Author-email: wufuheng@gmail.com
License: GPL
Keywords: motif,python
Platform: Independant
